{
  "Type": "ItemNameListTable",
  "Name": "DatItemSkillcardNameDataAsset",
  "Class": "UScriptClass'ItemNameListTable'",
  "Properties": {
    "Data": [
      "미사용",
      "아기",
      "아기라오",
      "아기다인",
      "마하라기",
      "마하라기온",
      "마하라기다인",
      "미사용",
      "갈",
      "갈라",
      "갈다인",
      "마하갈",
      "마하갈라",
      "마하갈다인",
      "부흐",
      "부흐라",
      "부흐다인",
      "마하부흐",
      "마하부흐라",
      "마하부흐다인",
      "지오",
      "지온가",
      "지오다인",
      "마하지오",
      "마하지온가",
      "마하지오다인",
      "메기도",
      "메기도라",
      "메기도라온",
      "코우하",
      "코우가",
      "코우가온",
      "마하코우하",
      "마하코우가",
      "마하코우가온",
      "신의 심판",
      "하마",
      "마한마",
      "하마온",
      "마한마온",
      "에이하",
      "에이가",
      "에이가온",
      "마하에이하",
      "마하에이가",
      "마하에이가온",
      "악마의 심판",
      "무드",
      "마하무드",
      "무드온",
      "마하무드온",
      "마린카린",
      "섹시 댄스",
      "네코다마시",
      "플래시 노이즈",
      "프린파",
      "텐타라후",
      "데빌 터치",
      "데빌 스마일",
      "망자의 탄식",
      "매리잡언",
      "종말의 예언",
      "포이즈마",
      "포이즌 미스트",
      "바이러스 브레스",
      "무거운 한숨",
      "무거운 공기",
      "흡혈",
      "흡마",
      "돌격",
      "어설트 다이브",
      "미사용",
      "전광석화",
      "소닉 펀치",
      "히트 웨이브",
      "기간 피스트",
      "아카샤 아츠",
      "갓 핸드",
      "미사용",
      "데드 엔드",
      "월영",
      "잔영",
      "뉴로 크런치",
      "미사용",
      "이검난무",
      "데스바운드",
      "장대비 베기",
      "미사용",
      "미사용",
      "파워 슬래시",
      "진공참",
      "브레이브 재퍼",
      "금강발파",
      "미사용",
      "싱글 샷",
      "미사용",
      "엔젤 애로",
      "밀리언 슛",
      "애로 샤워",
      "찰나 장대비 쏘기",
      "이노센트 턱",
      "공간살법",
      "미사용",
      "버스터 어택",
      "매드 어설트",
      "포이즌 애로",
      "디아",
      "디아라마",
      "디아라한",
      "메디아",
      "메디라마",
      "메디아라한",
      "메시아라이저",
      "파트라",
      "메파트라",
      "미사용",
      "미사용",
      "바이스디",
      "마하바이스디",
      "미사용",
      "암리타 드롭",
      "암리타 샤워",
      "리캄",
      "사마리캄",
      "타룬다",
      "마하타룬다",
      "스쿤다",
      "마하스쿤다",
      "라쿤다",
      "마하라쿤다",
      "데쿤다",
      "타루카쟈",
      "마하타루카쟈",
      "스쿠카쟈",
      "마하스쿠카쟈",
      "라쿠카쟈",
      "마하라쿠카쟈",
      "히트라이저",
      "랜더마이저",
      "차지",
      "컨센트레이트",
      "데카쟈",
      "테트라칸",
      "마카라칸",
      "리벨리온",
      "레볼루션",
      "화염 가드킬",
      "빙결 가드킬",
      "질풍 가드킬",
      "전격 가드킬",
      "미사용",
      "리캄드라",
      "미사용",
      "미사용",
      "참격 내성",
      "참격 무효",
      "참격 반사",
      "참격 흡수",
      "타격 내성",
      "타격 무효",
      "타격 반사",
      "타격 흡수",
      "관통 내성",
      "관통 무효",
      "관통 반사",
      "관통 흡수",
      "화염 내성",
      "화염 무효",
      "화염 반사",
      "화염 흡수",
      "빙결 내성",
      "빙결 무효",
      "빙결 반사",
      "빙결 흡수",
      "전격 내성",
      "전격 무효",
      "전격 반사",
      "전격 흡수",
      "질풍 내성",
      "질풍 무효",
      "질풍 반사",
      "질풍 흡수",
      "빛 내성",
      "빛 무효",
      "빛 반사",
      "어둠 내성",
      "어둠 무효",
      "어둠 반사",
      "뇌쇄 내성",
      "뇌쇄 무효",
      "동요 내성",
      "동요 무효",
      "혼란 내성",
      "혼란 무효",
      "공포 내성",
      "공포 무효",
      "자포자기 내성",
      "자포자기 무효",
      "동결 내성",
      "동결 무효",
      "감전 내성",
      "감전 무효",
      "독 내성",
      "독 무효",
      "부동심",
      "참격 회피",
      "진 참격 회피",
      "타격 회피",
      "진 타격 회피",
      "관통 회피",
      "진 관통 회피",
      "화염 회피",
      "진 화염 회피",
      "빙결 회피",
      "진 빙결 회피",
      "질풍 회피",
      "진 질풍 회피",
      "전격 회피",
      "진 전격 회피",
      "미사용",
      "대천사의 가호",
      "참격 부스터",
      "참격 하이부스터",
      "타격 부스터",
      "타격 하이부스터",
      "관통 부스터",
      "관통 하이부스터",
      "화염 부스터",
      "화염 하이부스터",
      "빙결 부스터",
      "빙결 하이부스터",
      "전격 부스터",
      "전격 하이부스터",
      "질풍 부스터",
      "질풍 하이부스터",
      "빛 부스터",
      "빛 하이부스터",
      "어둠 부스터",
      "어둠 하이부스터",
      "빛 흡수",
      "어둠 흡수",
      "미사용",
      "미사용",
      "카운터",
      "헤비 카운터",
      "하이퍼 카운터",
      "치유 촉진 소",
      "치유 촉진 중",
      "치유 촉진 대",
      "기공 소",
      "기공 중",
      "기공 대",
      "로우 그로우",
      "미들 그로우",
      "하이 그로우",
      "타루카쟈 오토",
      "라쿠카쟈 오토",
      "스쿠카쟈 오토",
      "미사용",
      "코칭",
      "어드바이스",
      "알리 댄스",
      "인왕 자세",
      "마술의 소양",
      "무도의 소양",
      "미사용",
      "미사용",
      "신들의 가호",
      "이 악물기",
      "불굴의 투지",
      "빛에서의 생환",
      "어둠에서의 생환",
      "마하라쿠카 오토",
      "마하타루카 오토",
      "마하스쿠카 오토",
      "미사용",
      "미사용",
      "미사용",
      "미사용",
      "미사용",
      "미사용",
      "상태 이상 성공률 UP",
      "하마 성공률 UP",
      "무드 성공률 UP",
      "빛에서의 대생환",
      "어둠에서의 대생환",
      "미사용",
      "승리의 숨결",
      "미사용",
      "물리 내성",
      "미사용",
      "상태 이상 내성",
      "미사용",
      "급속 회복",
      "순간 회복",
      "명왕의 가호",
      "리벨리온 오토",
      "크리티컬 UP",
      "크리티컬 대폭 UP",
      "미사용",
      "생환 트릭",
      "방염의 마음가짐",
      "방빙의 마음가짐",
      "방뢰의 마음가짐",
      "방풍의 마음가짐",
      "소울 시프트",
      "소울 체인",
      "진 소울 체인",
      "시프트 부스터",
      "시프트 하이부스터",
      "흡인의 재능",
      "싱글 부스터",
      "멀티 부스터",
      "빛 회피",
      "진 빛 회피",
      "어둠 회피",
      "진 어둠 회피",
      "만능 부스터",
      "미사용",
      "미사용",
      "미사용",
      "미사용",
      "미사용",
      "미사용",
      "미사용",
      "미사용",
      "미사용",
      "미사용",
      "미사용",
      "미사용",
      "미사용",
      "미사용",
      "미사용",
      "미사용",
      "미사용",
      "미사용",
      "미사용",
      "미사용",
      "미사용",
      "미사용",
      "미사용",
      "미사용",
      "미사용",
      "미사용",
      "미사용",
      "미사용",
      "미사용",
      "미사용",
      "미사용",
      "미사용",
      "미사용",
      "미사용",
      "미사용",
      "미사용",
      "미사용",
      "미사용",
      "미사용",
      "미사용",
      "미사용",
      "미사용",
      "미사용",
      "미사용",
      "미사용",
      "미사용",
      "미사용",
      "미사용",
      "미사용",
      "미사용",
      "미사용",
      "미사용",
      "미사용",
      "미사용",
      "미사용",
      "미사용",
      "미사용",
      "미사용",
      "미사용",
      "미사용",
      "미사용",
      "미사용",
      "미사용",
      "미사용",
      "미사용",
      "미사용",
      "미사용",
      "미사용",
      "미사용",
      "미사용",
      "미사용",
      "미사용",
      "미사용",
      "미사용",
      "미사용",
      "미사용",
      "미사용",
      "미사용",
      "미사용",
      "미사용",
      "미사용",
      "미사용",
      "미사용",
      "미사용",
      "미사용",
      "미사용",
      "미사용",
      "미사용",
      "미사용",
      "미사용",
      "미사용",
      "미사용",
      "미사용",
      "미사용",
      "미사용",
      "미사용",
      "미사용",
      "미사용",
      "미사용",
      "미사용",
      "미사용",
      "미사용",
      "미사용",
      "미사용",
      "미사용",
      "미사용",
      "미사용",
      "미사용",
      "미사용",
      "미사용",
      "미사용",
      "미사용",
      "미사용",
      "미사용",
      "미사용",
      "미사용",
      "미사용",
      "미사용",
      "미사용",
      "미사용",
      "미사용",
      "미사용",
      "미사용",
      "미사용",
      "미사용",
      "미사용",
      "미사용",
      "미사용",
      "미사용",
      "미사용",
      "미사용",
      "미사용",
      "미사용",
      "미사용",
      "미사용",
      "미사용",
      "미사용",
      "미사용",
      "미사용",
      "미사용",
      "미사용",
      "미사용",
      "미사용",
      "미사용",
      "미사용",
      "미사용",
      "미사용",
      "미사용",
      "미사용",
      "미사용",
      "미사용",
      "미사용",
      "미사용",
      "미사용",
      "미사용",
      "미사용",
      "미사용",
      "미사용",
      "미사용",
      "미사용",
      "미사용",
      "미사용",
      "미사용",
      "미사용",
      "미사용",
      "미사용",
      "미사용",
      "미사용",
      "미사용",
      "미사용",
      "미사용",
      "미사용",
      "미사용",
      "미사용",
      "미사용",
      "미사용",
      "미사용",
      "미사용",
      "미사용",
      "미사용",
      "미사용",
      "미사용",
      "미사용",
      "미사용",
      "미사용",
      "미사용",
      "미사용",
      "미사용",
      "미사용",
      "미사용",
      "미사용",
      "미사용",
      "미사용",
      "미사용"
    ]
  }
}