{
  "Type": "MiniMapIconListTable",
  "Name": "DatMiniMapIcon_304_101_001",
  "Class": "UScriptClass'MiniMapIconListTable'",
  "Properties": {
    "Data": [
      {
        "IconName": "UP",
        "SprType": 1,
        "SprNo": 11,
        "X": -26.0,
        "Y": -155.0,
        "DegreeAngle": 0.0,
        "VisibleFlag": "",
        "DisableFlag": ""
      },
      {
        "IconName": "上り階段",
        "SprType": 0,
        "SprNo": 44,
        "X": 10.0,
        "Y": -138.0,
        "DegreeAngle": 0.0,
        "VisibleFlag": "",
        "DisableFlag": ""
      }
    ]
  }
}