{
  "Type": "BmdAsset",
  "Name": "BMD_kfev600_CmmuNPC_005_900_cv",
  "Class": "UScriptClass'BmdAsset'",
  "Properties": {
    "mBuf": [
      7,
      0,
      0,
      0,
      0,
      0,
      13,
      -81,
      49,
      71,
      83,
      77,
      0,
      0,
      0,
      0,
      0,
      0,
      13,
      -120,
      0,
      0,
      0,
      39,
      0,
      0,
      0,
      13,
      0,
      0,
      0,
      2,
      0,
      0,
      0,
      0,
      0,
      0,
      0,
      120,
      0,
      0,
      0,
      0,
      0,
      0,
      1,
      92,
      0,
      0,
      0,
      0,
      0,
      0,
      2,
      72,
      0,
      0,
      0,
      1,
      0,
      0,
      3,
      -28,
      0,
      0,
      0,
      0,
      0,
      0,
      4,
      72,
      0,
      0,
      0,
      0,
      0,
      0,
      4,
      -20,
      0,
      0,
      0,
      0,
      0,
      0,
      5,
      -36,
      0,
      0,
      0,
      0,
      0,
      0,
      7,
      -72,
      0,
      0,
      0,
      0,
      0,
      0,
      8,
      -96,
      0,
      0,
      0,
      0,
      0,
      0,
      10,
      -72,
      0,
      0,
      0,
      0,
      0,
      0,
      11,
      -84,
      0,
      0,
      0,
      0,
      0,
      0,
      12,
      68,
      0,
      0,
      0,
      0,
      0,
      0,
      12,
      -40,
      0,
      0,
      13,
      68,
      0,
      0,
      0,
      2,
      0,
      0,
      0,
      0,
      0,
      0,
      0,
      0,
      77,
      83,
      71,
      95,
      48,
      48,
      48,
      95,
      48,
      95,
      48,
      0,
      0,
      0,
      0,
      0,
      0,
      0,
      0,
      0,
      0,
      0,
      0,
      0,
      0,
      2,
      0,
      0,
      0,
      0,
      0,
      -96,
      0,
      0,
      0,
      -5,
      0,
      0,
      0,
      -71,
      -2,
      -14,
      5,
      -1,
      -1,
      -2,
      -15,
      65,
      -2,
      -9,
      -123,
      104,
      1,
      2,
      1,
      0,
      0,
      0,
      0,
      1,
      1,
      1,
      1,
      -2,
      -9,
      97,
      2,
      1,
      1,
      1,
      5,
      1,
      2,
      1,
      1,
      1,
      1,
      1,
      -27,
      -109,
      -114,
      -27,
      -111,
      -128,
      -27,
      -111,
      -128,
      -17,
      -68,
      -116,
      -27,
      -91,
      -67,
      -28,
      -71,
      -123,
      -28,
      -72,
      -115,
      -24,
      -90,
      -117,
      -27,
      -107,
      -118,
      -29,
      -128,
      -126,
      10,
      -23,
      -128,
      -103,
      -28,
      -72,
      -115,
      -26,
      -104,
      -81,
      -2,
      -15,
      -126,
      -27,
      -105,
      -114,
      -17,
      -68,
      -97,
      10,
      -2,
      -15,
      33,
      -2,
      -14,
      5,
      -1,
      -1,
      -2,
      -15,
      65,
      -2,
      -9,
      -123,
      104,
      1,
      2,
      1,
      0,
      0,
      0,
      0,
      1,
      1,
      1,
      1,
      -2,
      -9,
      97,
      2,
      1,
      1,
      1,
      5,
      1,
      3,
      1,
      1,
      1,
      1,
      1,
      -28,
      -72,
      -128,
      -26,
      -82,
      -75,
      -26,
      -103,
      -126,
      -23,
      -106,
      -109,
      -26,
      -78,
      -110,
      -24,
      -90,
      -117,
      -17,
      -68,
      -116,
      13,
      10,
      -28,
      -67,
      -96,
      -27,
      -113,
      -120,
      -23,
      -107,
      -73,
      -27,
      -66,
      -105,
      -26,
      -101,
      -76,
      -23,
      -85,
      -104,
      -27,
      -92,
      -89,
      -28,
      -70,
      -122,
      -17,
      -68,
      -127,
      13,
      10,
      -2,
      -15,
      33,
      0,
      0,
      0,
      0,
      77,
      83,
      71,
      95,
      48,
      48,
      49,
      95,
      48,
      95,
      48,
      0,
      0,
      0,
      0,
      0,
      0,
      0,
      0,
      0,
      0,
      0,
      0,
      0,
      0,
      2,
      0,
      1,
      0,
      0,
      1,
      -124,
      0,
      0,
      1,
      -21,
      0,
      0,
      0,
      -63,
      -2,
      -14,
      5,
      -1,
      -1,
      -2,
      -15,
      65,
      -2,
      -9,
      -123,
      105,
      1,
      2,
      1,
      0,
      0,
      0,
      0,
      1,
      1,
      1,
      1,
      -2,
      -9,
      97,
      2,
      1,
      1,
      1,
      5,
      1,
      4,
      1,
      1,
      1,
      1,
      1,
      -24,
      -128,
      -127,
      -25,
      -120,
      -70,
      -27,
      -83,
      -112,
      -28,
      -67,
      -96,
      -25,
      -100,
      -97,
      -26,
      -104,
      -81,
      -25,
      -102,
      -124,
      -17,
      -68,
      -116,
      10,
      -28,
      -70,
      -70,
      -26,
      -119,
      -115,
      -28,
      -72,
      -115,
      -26,
      -100,
      -125,
      -28,
      -72,
      -128,
      -28,
      -72,
      -117,
      -27,
      -83,
      -112,
      -27,
      -80,
      -79,
      -23,
      -107,
      -73,
      -27,
      -92,
      -89,
      -27,
      -107,
      -90,
      -29,
      -128,
      -126,
      10,
      -2,
      -15,
      33,
      -2,
      -14,
      5,
      -1,
      -1,
      -2,
      -15,
      65,
      -2,
      -9,
      -123,
      105,
      1,
      2,
      1,
      0,
      0,
      0,
      0,
      1,
      1,
      1,
      1,
      -2,
      -9,
      97,
      2,
      1,
      1,
      1,
      5,
      1,
      5,
      1,
      1,
      1,
      1,
      1,
      -28,
      -72,
      -128,
      -27,
      -82,
      -102,
      -26,
      -104,
      -81,
      -26,
      -120,
      -111,
      -27,
      -128,
      -111,
      -24,
      -82,
      -118,
      -25,
      -97,
      -82,
      -28,
      -70,
      -122,
      -29,
      -128,
      -126,
      13,
      10,
      -28,
      -67,
      -96,
      -24,
      -86,
      -86,
      -26,
      -104,
      -81,
      -28,
      -72,
      -115,
      -26,
      -104,
      -81,
      -17,
      -68,
      -97,
      10,
      -2,
      -15,
      33,
      0,
      0,
      0,
      0,
      77,
      83,
      71,
      95,
      48,
      48,
      50,
      95,
      48,
      95,
      48,
      0,
      0,
      0,
      0,
      0,
      0,
      0,
      0,
      0,
      0,
      0,
      0,
      0,
      0,
      4,
      0,
      0,
      0,
      0,
      2,
      120,
      0,
      0,
      2,
      -37,
      0,
      0,
      3,
      27,
      0,
      0,
      3,
      111,
      0,
      0,
      1,
      105,
      -2,
      -14,
      5,
      -1,
      -1,
      -2,
      -15,
      65,
      -2,
      -9,
      -123,
      104,
      1,
      2,
      1,
      0,
      0,
      0,
      0,
      1,
      1,
      1,
      1,
      -2,
      -9,
      97,
      2,
      1,
      1,
      1,
      5,
      1,
      6,
      1,
      1,
      1,
      1,
      1,
      -27,
      -111,
      -75,
      -27,
      -111,
      -75,
      -27,
      -111,
      -75,
      -17,
      -68,
      -116,
      -27,
      -114,
      -97,
      -28,
      -66,
      -122,
      -26,
      -104,
      -81,
      -23,
      -128,
      -103,
      -26,
      -88,
      -93,
      -27,
      -107,
      -118,
      -17,
      -68,
      -127,
      13,
      10,
      -24,
      -94,
      -85,
      -27,
      -80,
      -121,
      -28,
      -70,
      -122,
      -28,
      -72,
      -128,
      -24,
      -69,
      -115,
      -27,
      -107,
      -90,
      -29,
      -128,
      -126,
      13,
      10,
      -2,
      -15,
      33,
      -2,
      -14,
      5,
      -1,
      -1,
      -2,
      -15,
      65,
      -2,
      -9,
      -123,
      104,
      1,
      1,
      1,
      0,
      0,
      0,
      0,
      1,
      1,
      1,
      1,
      -2,
      -9,
      97,
      2,
      1,
      1,
      1,
      5,
      1,
      7,
      1,
      1,
      1,
      1,
      1,
      -30,
      -128,
      -90,
      -30,
      -128,
      -90,
      -26,
      -120,
      -111,
      -24,
      -86,
      -86,
      -17,
      -68,
      -116,
      -2,
      -15,
      -126,
      -29,
      -128,
      -126,
      13,
      10,
      -2,
      -15,
      33,
      -2,
      -14,
      5,
      -1,
      -1,
      -2,
      -15,
      65,
      -2,
      -9,
      -123,
      104,
      1,
      1,
      1,
      0,
      0,
      0,
      0,
      1,
      1,
      1,
      1,
      -2,
      -9,
      97,
      2,
      1,
      1,
      1,
      5,
      1,
      8,
      1,
      1,
      1,
      1,
      1,
      -26,
      -120,
      -111,
      -26,
      -119,
      -109,
      -25,
      -82,
      -105,
      -27,
      -66,
      -71,
      -27,
      -70,
      -107,
      -26,
      -108,
      -71,
      -27,
      -69,
      -70,
      -23,
      -128,
      -103,
      -23,
      -106,
      -109,
      -29,
      -128,
      -116,
      -26,
      -101,
      -72,
      -24,
      -97,
      -78,
      -29,
      -128,
      -115,
      -29,
      -128,
      -126,
      10,
      -2,
      -15,
      33,
      -2,
      -14,
      5,
      -1,
      -1,
      -2,
      -15,
      65,
      -2,
      -9,
      -123,
      104,
      1,
      2,
      1,
      0,
      0,
      0,
      0,
      1,
      1,
      1,
      1,
      -2,
      -9,
      97,
      2,
      1,
      1,
      1,
      5,
      1,
      9,
      1,
      1,
      1,
      1,
      1,
      -24,
      -90,
      -127,
      -26,
      -108,
      -71,
      -27,
      -69,
      -70,
      -26,
      -120,
      -112,
      -26,
      -72,
      -123,
      -26,
      -106,
      -80,
      -27,
      -113,
      -120,
      -27,
      -119,
      -115,
      -24,
      -95,
      -101,
      -25,
      -102,
      -124,
      -27,
      -70,
      -105,
      -17,
      -68,
      -116,
      10,
      -28,
      -72,
      -115,
      -26,
      -100,
      -125,
      -24,
      -68,
      -72,
      -25,
      -75,
      -90,
      -26,
      -100,
      -120,
      -23,
      -85,
      -104,
      -25,
      -102,
      -124,
      -26,
      -106,
      -80,
      -26,
      -96,
      -95,
      -24,
      -120,
      -115,
      -17,
      -68,
      -127,
      13,
      10,
      -2,
      -15,
      33,
      0,
      0,
      0,
      0,
      83,
      69,
      76,
      95,
      48,
      48,
      51,
      95,
      48,
      95,
      48,
      0,
      0,
      0,
      0,
      0,
      0,
      0,
      0,
      0,
      0,
      0,
      0,
      0,
      0,
      0,
      0,
      2,
      0,
      0,
      0,
      0,
      0,
      0,
      4,
      16,
      0,
      0,
      4,
      43,
      0,
      0,
      0,
      55,
      -2,
      -14,
      5,
      -1,
      -1,
      -2,
      -15,
      65,
      -23,
      -128,
      -103,
      -27,
      -128,
      -117,
      -28,
      -72,
      -69,
      -26,
      -124,
      -113,
      -28,
      -72,
      -115,
      -23,
      -116,
      -81,
      0,
      -2,
      -14,
      5,
      -1,
      -1,
      -2,
      -15,
      65,
      -26,
      -78,
      -110,
      -26,
      -100,
      -119,
      -27,
      -65,
      -123,
      -24,
      -90,
      -127,
      -26,
      -108,
      -71,
      -24,
      -82,
      -118,
      0,
      0,
      0,
      77,
      83,
      71,
      95,
      48,
      48,
      52,
      95,
      48,
      95,
      48,
      0,
      0,
      0,
      0,
      0,
      0,
      0,
      0,
      0,
      0,
      0,
      0,
      0,
      0,
      1,
      0,
      0,
      0,
      0,
      4,
      108,
      0,
      0,
      0,
      126,
      -2,
      -14,
      5,
      -1,
      -1,
      -2,
      -15,
      65,
      -2,
      -9,
      -123,
      104,
      1,
      2,
      1,
      0,
      0,
      0,
      0,
      1,
      1,
      1,
      1,
      -2,
      -9,
      97,
      2,
      1,
      1,
      1,
      5,
      1,
      10,
      1,
      1,
      1,
      1,
      1,
      -27,
      -80,
      -115,
      -27,
      -112,
      -89,
      -17,
      -68,
      -97,
      -23,
      -126,
      -93,
      -26,
      -120,
      -111,
      -27,
      -114,
      -69,
      -24,
      -73,
      -97,
      -24,
      -128,
      -127,
      -27,
      -87,
      -122,
      -27,
      -83,
      -112,
      -27,
      -91,
      -67,
      -27,
      -91,
      -67,
      -27,
      -107,
      -122,
      -23,
      -121,
      -113,
      -17,
      -68,
      -116,
      13,
      10,
      -26,
      -118,
      -118,
      -23,
      -128,
      -103,
      -23,
      -106,
      -109,
      -27,
      -70,
      -105,
      -27,
      -68,
      -124,
      -27,
      -66,
      -105,
      -26,
      -101,
      -76,
      -27,
      -91,
      -67,
      -26,
      -101,
      -76,
      -26,
      -93,
      -110,
      -27,
      -112,
      -89,
      -17,
      -68,
      -127,
      10,
      -2,
      -15,
      33,
      0,
      0,
      0,
      77,
      83,
      71,
      95,
      48,
      48,
      53,
      95,
      48,
      95,
      48,
      0,
      0,
      0,
      0,
      0,
      0,
      0,
      0,
      0,
      0,
      0,
      0,
      0,
      0,
      2,
      0,
      0,
      0,
      0,
      5,
      20,
      0,
      0,
      5,
      86,
      0,
      0,
      0,
      -58,
      -2,
      -14,
      5,
      -1,
      -1,
      -2,
      -15,
      65,
      -2,
      -9,
      -123,
      104,
      1,
      1,
      1,
      0,
      0,
      0,
      0,
      1,
      1,
      1,
      1,
      -2,
      -9,
      97,
      2,
      1,
      1,
      1,
      5,
      1,
      11,
      1,
      1,
      1,
      1,
      1,
      -27,
      -109,
      -114,
      -27,
      -111,
      -128,
      -17,
      -68,
      -116,
      -26,
      -104,
      -81,
      -23,
      -128,
      -103,
      -26,
      -88,
      -93,
      -27,
      -105,
      -114,
      -17,
      -68,
      -97,
      10,
      -2,
      -15,
      33,
      -2,
      -14,
      5,
      -1,
      -1,
      -2,
      -15,
      65,
      -2,
      -9,
      -123,
      104,
      1,
      2,
      1,
      0,
      0,
      0,
      0,
      1,
      1,
      1,
      1,
      -2,
      -9,
      97,
      2,
      1,
      1,
      1,
      5,
      1,
      12,
      1,
      1,
      1,
      1,
      1,
      -28,
      -67,
      -96,
      -23,
      -128,
      -103,
      -24,
      -87,
      -79,
      -28,
      -71,
      -97,
      -24,
      -82,
      -109,
      -26,
      -120,
      -111,
      -26,
      -116,
      -70,
      -23,
      -85,
      -104,
      -24,
      -120,
      -120,
      -25,
      -102,
      -124,
      -17,
      -68,
      -116,
      13,
      10,
      -27,
      -67,
      -73,
      -27,
      -67,
      -65,
      -27,
      -100,
      -88,
      -25,
      -88,
      -79,
      -24,
      -82,
      -102,
      -24,
      -121,
      -77,
      -28,
      -69,
      -118,
      -25,
      -126,
      -70,
      -26,
      -83,
      -94,
      -26,
      -120,
      -111,
      -27,
      -128,
      -111,
      -26,
      -119,
      -128,
      -28,
      -67,
      -100,
      -25,
      -102,
      -124,
      -27,
      -118,
      -86,
      -27,
      -118,
      -101,
      -27,
      -111,
      -94,
      -29,
      -128,
      -126,
      10,
      -2,
      -15,
      33,
      0,
      0,
      0,
      77,
      83,
      71,
      95,
      48,
      48,
      54,
      95,
      48,
      95,
      48,
      0,
      0,
      0,
      0,
      0,
      0,
      0,
      0,
      0,
      0,
      0,
      0,
      0,
      0,
      4,
      0,
      1,
      0,
      0,
      6,
      12,
      0,
      0,
      6,
      115,
      0,
      0,
      6,
      -45,
      0,
      0,
      7,
      56,
      0,
      0,
      1,
      -86,
      -2,
      -14,
      5,
      -1,
      -1,
      -2,
      -15,
      65,
      -2,
      -9,
      -123,
      105,
      1,
      2,
      1,
      0,
      0,
      0,
      0,
      1,
      1,
      1,
      1,
      -2,
      -9,
      97,
      2,
      1,
      1,
      1,
      5,
      1,
      13,
      1,
      1,
      1,
      1,
      1,
      -24,
      -86,
      -86,
      -27,
      -120,
      -80,
      -26,
      -106,
      -80,
      -26,
      -96,
      -95,
      -24,
      -120,
      -115,
      -17,
      -68,
      -116,
      10,
      -27,
      -83,
      -72,
      -26,
      -96,
      -95,
      -26,
      -79,
      -70,
      -27,
      -82,
      -102,
      -24,
      -90,
      -127,
      -25,
      -89,
      -69,
      -26,
      -92,
      -115,
      -23,
      -126,
      -93,
      -26,
      -93,
      -75,
      -26,
      -97,
      -65,
      -27,
      -83,
      -112,
      -26,
      -88,
      -71,
      -28,
      -70,
      -122,
      -29,
      -128,
      -126,
      10,
      -2,
      -15,
      33,
      -2,
      -14,
      5,
      -1,
      -1,
      -2,
      -15,
      65,
      -2,
      -9,
      -123,
      105,
      1,
      2,
      1,
      0,
      0,
      0,
      0,
      1,
      1,
      1,
      1,
      -2,
      -9,
      97,
      2,
      1,
      1,
      1,
      5,
      1,
      14,
      1,
      1,
      1,
      1,
      1,
      -24,
      -86,
      -86,
      -26,
      -104,
      -81,
      -24,
      -90,
      -127,
      -25,
      -119,
      -71,
      -27,
      -120,
      -91,
      -25,
      -89,
      -69,
      -26,
      -92,
      -115,
      -27,
      -120,
      -80,
      -24,
      -125,
      -67,
      -27,
      -92,
      -96,
      -28,
      -65,
      -81,
      -25,
      -98,
      -80,
      -26,
      -96,
      -95,
      -27,
      -100,
      -110,
      -25,
      -102,
      -124,
      -23,
      -85,
      -104,
      -27,
      -100,
      -80,
      -29,
      -128,
      -126,
      10,
      -2,
      -15,
      33,
      -2,
      -14,
      5,
      -1,
      -1,
      -2,
      -15,
      65,
      -2,
      -9,
      -123,
      105,
      1,
      4,
      1,
      0,
      0,
      0,
      0,
      1,
      1,
      1,
      1,
      -2,
      -9,
      97,
      2,
      1,
      1,
      1,
      5,
      1,
      15,
      1,
      1,
      1,
      1,
      1,
      -23,
      -126,
      -93,
      -27,
      -83,
      -87,
      -27,
      -83,
      -112,
      -28,
      -69,
      -118,
      -27,
      -66,
      -116,
      -28,
      -71,
      -97,
      -24,
      -125,
      -67,
      -27,
      -92,
      -96,
      10,
      -25,
      -71,
      -68,
      -25,
      -70,
      -116,
      -27,
      -82,
      -120,
      -24,
      -83,
      -73,
      -24,
      -111,
      -105,
      -24,
      -88,
      -79,
      -27,
      -92,
      -102,
      -27,
      -83,
      -72,
      -25,
      -108,
      -97,
      -30,
      -128,
      -90,
      -30,
      -128,
      -90,
      13,
      10,
      -2,
      -15,
      33,
      -2,
      -14,
      5,
      -1,
      -1,
      -2,
      -15,
      65,
      -2,
      -9,
      -123,
      105,
      1,
      4,
      1,
      0,
      0,
      0,
      0,
      1,
      1,
      1,
      1,
      -2,
      -9,
      97,
      2,
      1,
      1,
      1,
      5,
      1,
      16,
      1,
      1,
      1,
      1,
      1,
      -30,
      -128,
      -90,
      -30,
      -128,
      -90,
      -27,
      -115,
      -77,
      -28,
      -67,
      -65,
      -25,
      -97,
      -91,
      -23,
      -127,
      -109,
      -26,
      -97,
      -65,
      -27,
      -83,
      -112,
      -26,
      -88,
      -71,
      -28,
      -72,
      -90,
      -28,
      -72,
      -115,
      -26,
      -104,
      -81,
      -23,
      -126,
      -93,
      -27,
      -83,
      -87,
      -27,
      -83,
      -112,
      -17,
      -68,
      -116,
      10,
      -28,
      -67,
      -122,
      -26,
      -120,
      -111,
      -23,
      -126,
      -124,
      -26,
      -104,
      -81,
      -24,
      -90,
      -70,
      -27,
      -66,
      -105,
      -27,
      -66,
      -120,
      -23,
      -85,
      -104,
      -24,
      -120,
      -120,
      -30,
      -128,
      -90,
      -30,
      -128,
      -90,
      13,
      10,
      -2,
      -15,
      33,
      0,
      0,
      0,
      77,
      83,
      71,
      95,
      48,
      48,
      55,
      95,
      48,
      95,
      48,
      0,
      0,
      0,
      0,
      0,
      0,
      0,
      0,
      0,
      0,
      0,
      0,
      0,
      0,
      2,
      0,
      0,
      0,
      0,
      7,
      -32,
      0,
      0,
      8,
      77,
      0,
      0,
      0,
      -64,
      -2,
      -14,
      5,
      -1,
      -1,
      -2,
      -15,
      65,
      -2,
      -9,
      -123,
      104,
      1,
      1,
      1,
      0,
      0,
      0,
      0,
      1,
      1,
      1,
      1,
      -2,
      -9,
      97,
      2,
      1,
      1,
      1,
      5,
      1,
      17,
      1,
      1,
      1,
      1,
      1,
      -24,
      -128,
      -127,
      -27,
      -87,
      -122,
      -27,
      -83,
      -112,
      -24,
      -127,
      -67,
      -27,
      -120,
      -80,
      -23,
      -128,
      -103,
      -27,
      -128,
      -117,
      -26,
      -74,
      -120,
      -26,
      -127,
      -81,
      -28,
      -71,
      -117,
      -27,
      -66,
      -116,
      -17,
      -68,
      -116,
      10,
      -27,
      -113,
      -81,
      -26,
      -104,
      -81,
      -28,
      -72,
      -128,
      -25,
      -101,
      -76,
      -27,
      -109,
      -83,
      -27,
      -128,
      -117,
      -28,
      -72,
      -115,
      -27,
      -127,
      -100,
      -27,
      -111,
      -94,
      -29,
      -128,
      -126,
      10,
      -2,
      -15,
      33,
      -2,
      -14,
      5,
      -1,
      -1,
      -2,
      -15,
      65,
      -2,
      -9,
      -123,
      104,
      1,
      2,
      1,
      0,
      0,
      0,
      0,
      1,
      1,
      1,
      1,
      -2,
      -9,
      97,
      2,
      1,
      1,
      1,
      5,
      1,
      18,
      1,
      1,
      1,
      1,
      1,
      -28,
      -66,
      -122,
      -17,
      -68,
      -116,
      -25,
      -84,
      -111,
      -28,
      -72,
      -128,
      -27,
      -128,
      -117,
      -25,
      -84,
      -111,
      -28,
      -72,
      -128,
      -27,
      -128,
      -117,
      -17,
      -67,
      -98,
      -27,
      -107,
      -118,
      -27,
      -109,
      -120,
      -27,
      -109,
      -120,
      -29,
      -128,
      -126,
      13,
      10,
      -2,
      -15,
      33,
      0,
      77,
      83,
      71,
      95,
      48,
      48,
      56,
      95,
      48,
      95,
      48,
      0,
      0,
      0,
      0,
      0,
      0,
      0,
      0,
      0,
      0,
      0,
      0,
      0,
      0,
      5,
      0,
      1,
      0,
      0,
      8,
      -44,
      0,
      0,
      9,
      44,
      0,
      0,
      9,
      -81,
      0,
      0,
      10,
      1,
      0,
      0,
      10,
      83,
      0,
      0,
      1,
      -31,
      -2,
      -14,
      5,
      -1,
      -1,
      -2,
      -15,
      65,
      -2,
      -9,
      -123,
      105,
      1,
      2,
      1,
      0,
      0,
      0,
      0,
      1,
      1,
      1,
      1,
      -2,
      -9,
      97,
      2,
      1,
      1,
      1,
      5,
      1,
      19,
      1,
      1,
      1,
      1,
      1,
      -27,
      -109,
      -114,
      -27,
      -111,
      -128,
      -24,
      -128,
      -127,
      -25,
      -120,
      -70,
      -27,
      -83,
      -112,
      -17,
      -68,
      -116,
      -28,
      -67,
      -96,
      -25,
      -102,
      -124,
      -27,
      -127,
      -121,
      -25,
      -119,
      -103,
      -26,
      -114,
      -119,
      -27,
      -121,
      -70,
      -28,
      -66,
      -122,
      -28,
      -70,
      -122,
      -29,
      -128,
      -126,
      13,
      10,
      -2,
      -15,
      33,
      -2,
      -14,
      5,
      -1,
      -1,
      -2,
      -15,
      65,
      -2,
      -9,
      -123,
      105,
      1,
      1,
      1,
      0,
      0,
      0,
      0,
      1,
      1,
      1,
      1,
      -2,
      -9,
      97,
      2,
      1,
      1,
      1,
      5,
      1,
      20,
      1,
      1,
      1,
      1,
      1,
      -30,
      -128,
      -90,
      -30,
      -128,
      -90,
      -26,
      -119,
      -128,
      -28,
      -69,
      -91,
      -27,
      -107,
      -118,
      -17,
      -68,
      -116,
      -25,
      -126,
      -70,
      -28,
      -70,
      -122,
      -24,
      -125,
      -67,
      -27,
      -92,
      -96,
      -27,
      -71,
      -85,
      -27,
      -118,
      -87,
      -26,
      -100,
      -120,
      -23,
      -85,
      -104,
      -25,
      -102,
      -124,
      -27,
      -83,
      -72,
      -25,
      -108,
      -97,
      -27,
      -128,
      -111,
      -17,
      -68,
      -116,
      13,
      10,
      -26,
      -120,
      -111,
      -27,
      -128,
      -111,
      -28,
      -71,
      -97,
      -26,
      -100,
      -125,
      -26,
      -101,
      -76,
      -27,
      -118,
      -96,
      -27,
      -118,
      -86,
      -27,
      -118,
      -101,
      -25,
      -102,
      -124,
      -29,
      -128,
      -126,
      10,
      -2,
      -15,
      33,
      -2,
      -14,
      5,
      -1,
      -1,
      -2,
      -15,
      65,
      -2,
      -9,
      -123,
      105,
      1,
      1,
      1,
      0,
      0,
      0,
      0,
      1,
      1,
      1,
      1,
      -2,
      -9,
      97,
      2,
      1,
      1,
      1,
      5,
      1,
      21,
      1,
      1,
      1,
      1,
      1,
      -28,
      -67,
      -96,
      -25,
      -100,
      -97,
      -25,
      -102,
      -124,
      -30,
      -128,
      -90,
      -30,
      -128,
      -90,
      -23,
      -107,
      -73,
      -27,
      -92,
      -89,
      -28,
      -70,
      -122,
      -27,
      -111,
      -94,
      -17,
      -68,
      -116,
      10,
      -2,
      -15,
      -126,
      -30,
      -128,
      -90,
      -30,
      -128,
      -90,
      10,
      -2,
      -15,
      33,
      -2,
      -14,
      5,
      -1,
      -1,
      -2,
      -15,
      65,
      -2,
      -9,
      -123,
      105,
      1,
      1,
      1,
      0,
      0,
      0,
      0,
      1,
      1,
      1,
      1,
      -2,
      -9,
      97,
      2,
      1,
      1,
      1,
      5,
      1,
      22,
      1,
      1,
      1,
      1,
      1,
      -25,
      -100,
      -117,
      -28,
      -66,
      -122,
      -28,
      -67,
      -96,
      -24,
      -73,
      -88,
      -24,
      -74,
      -118,
      -28,
      -70,
      -122,
      -28,
      -69,
      -128,
      -23,
      -70,
      -68,
      -23,
      -101,
      -93,
      -23,
      -105,
      -100,
      -27,
      -111,
      -94,
      -30,
      -128,
      -90,
      -30,
      -128,
      -90,
      13,
      10,
      -2,
      -15,
      33,
      -2,
      -14,
      5,
      -1,
      -1,
      -2,
      -15,
      65,
      -2,
      -9,
      -123,
      105,
      1,
      2,
      1,
      0,
      0,
      0,
      0,
      1,
      1,
      1,
      1,
      -2,
      -9,
      97,
      2,
      1,
      1,
      1,
      5,
      1,
      23,
      1,
      1,
      1,
      1,
      1,
      -26,
      -83,
      -95,
      -24,
      -65,
      -114,
      -28,
      -67,
      -96,
      -23,
      -102,
      -88,
      -26,
      -103,
      -126,
      -27,
      -122,
      -115,
      -28,
      -66,
      -122,
      -27,
      -70,
      -105,
      -24,
      -93,
      -95,
      -17,
      -68,
      -116,
      10,
      -26,
      -120,
      -111,
      -27,
      -128,
      -111,
      -26,
      -100,
      -125,
      -25,
      -83,
      -119,
      -28,
      -67,
      -96,
      -25,
      -102,
      -124,
      -30,
      -128,
      -90,
      -30,
      -128,
      -90,
      10,
      -2,
      -15,
      33,
      0,
      0,
      0,
      0,
      77,
      83,
      71,
      95,
      48,
      48,
      57,
      95,
      48,
      95,
      48,
      0,
      0,
      0,
      0,
      0,
      0,
      0,
      0,
      0,
      0,
      0,
      0,
      0,
      0,
      2,
      0,
      0,
      0,
      0,
      10,
      -32,
      0,
      0,
      11,
      79,
      0,
      0,
      0,
      -53,
      -2,
      -14,
      5,
      -1,
      -1,
      -2,
      -15,
      65,
      -2,
      -9,
      -123,
      104,
      1,
      1,
      1,
      0,
      0,
      0,
      0,
      1,
      1,
      1,
      1,
      -2,
      -9,
      97,
      2,
      1,
      1,
      1,
      5,
      1,
      24,
      1,
      1,
      1,
      1,
      1,
      -27,
      -113,
      -86,
      -24,
      -90,
      -127,
      -24,
      -82,
      -109,
      -2,
      -15,
      -126,
      -27,
      -71,
      -85,
      -27,
      -65,
      -103,
      -27,
      -82,
      -93,
      -27,
      -126,
      -77,
      -17,
      -68,
      -116,
      13,
      10,
      -26,
      -100,
      -120,
      -23,
      -85,
      -104,
      -25,
      -102,
      -124,
      -27,
      -83,
      -72,
      -25,
      -108,
      -97,
      -27,
      -80,
      -79,
      -26,
      -100,
      -125,
      -24,
      -100,
      -126,
      -26,
      -109,
      -127,
      -24,
      -128,
      -116,
      -24,
      -121,
      -77,
      -27,
      -101,
      -119,
      -17,
      -68,
      -127,
      13,
      10,
      -2,
      -15,
      33,
      -2,
      -14,
      5,
      -1,
      -1,
      -2,
      -15,
      65,
      -2,
      -9,
      -123,
      104,
      1,
      1,
      1,
      0,
      0,
      0,
      0,
      1,
      1,
      1,
      1,
      -2,
      -9,
      97,
      2,
      1,
      1,
      1,
      5,
      1,
      25,
      1,
      1,
      1,
      1,
      1,
      -30,
      -128,
      -90,
      -30,
      -128,
      -90,
      -26,
      -120,
      -111,
      -24,
      -86,
      -86,
      -24,
      -128,
      -127,
      -27,
      -87,
      -122,
      -27,
      -83,
      -112,
      -17,
      -68,
      -116,
      10,
      -23,
      -128,
      -103,
      -27,
      -128,
      -117,
      -28,
      -72,
      -69,
      -26,
      -124,
      -113,
      -28,
      -72,
      -115,
      -23,
      -116,
      -81,
      -27,
      -112,
      -89,
      -17,
      -68,
      -97,
      10,
      -2,
      -15,
      33,
      0,
      0,
      77,
      83,
      71,
      95,
      48,
      49,
      48,
      95,
      48,
      95,
      48,
      0,
      0,
      0,
      0,
      0,
      0,
      0,
      0,
      0,
      0,
      0,
      0,
      0,
      0,
      1,
      0,
      1,
      0,
      0,
      11,
      -48,
      0,
      0,
      0,
      114,
      -2,
      -14,
      5,
      -1,
      -1,
      -2,
      -15,
      65,
      -2,
      -9,
      -123,
      105,
      1,
      1,
      1,
      0,
      0,
      0,
      0,
      1,
      1,
      1,
      1,
      -2,
      -9,
      97,
      2,
      1,
      1,
      1,
      5,
      1,
      26,
      1,
      1,
      1,
      1,
      1,
      -24,
      -128,
      -127,
      -25,
      -120,
      -70,
      -27,
      -83,
      -112,
      -28,
      -67,
      -96,
      -27,
      -111,
      -128,
      -30,
      -128,
      -90,
      -30,
      -128,
      -90,
      -23,
      -128,
      -103,
      -26,
      -88,
      -93,
      -26,
      -100,
      -125,
      -25,
      -75,
      -90,
      -28,
      -70,
      -70,
      -27,
      -82,
      -74,
      -26,
      -73,
      -69,
      -23,
      -70,
      -69,
      -25,
      -123,
      -87,
      -25,
      -102,
      -124,
      -29,
      -128,
      -126,
      10,
      -27,
      -80,
      -115,
      -27,
      -112,
      -89,
      -17,
      -68,
      -116,
      -2,
      -15,
      -126,
      -17,
      -68,
      -97,
      13,
      10,
      -2,
      -15,
      33,
      0,
      0,
      0,
      77,
      83,
      71,
      95,
      48,
      49,
      49,
      95,
      48,
      95,
      48,
      0,
      0,
      0,
      0,
      0,
      0,
      0,
      0,
      0,
      0,
      0,
      0,
      0,
      0,
      1,
      0,
      0,
      0,
      0,
      12,
      104,
      0,
      0,
      0,
      111,
      -2,
      -14,
      5,
      -1,
      -1,
      -2,
      -15,
      65,
      -2,
      -9,
      -123,
      104,
      1,
      2,
      1,
      0,
      0,
      0,
      0,
      1,
      1,
      1,
      1,
      -2,
      -9,
      97,
      2,
      1,
      1,
      1,
      5,
      1,
      27,
      1,
      1,
      1,
      1,
      1,
      -27,
      -120,
      -91,
      -26,
      -118,
      -118,
      -24,
      -87,
      -79,
      -24,
      -84,
      -101,
      -27,
      -66,
      -105,
      -23,
      -128,
      -103,
      -23,
      -70,
      -68,
      -25,
      -103,
      -67,
      -27,
      -107,
      -118,
      -29,
      -128,
      -126,
      10,
      -25,
      -107,
      -94,
      -25,
      -85,
      -97,
      -2,
      -15,
      -126,
      -27,
      -80,
      -79,
      -27,
      -125,
      -113,
      -26,
      -120,
      -111,
      -27,
      -128,
      -111,
      -25,
      -102,
      -124,
      -27,
      -83,
      -85,
      -27,
      -83,
      -112,
      -27,
      -104,
      -101,
      -17,
      -68,
      -127,
      13,
      10,
      -2,
      -15,
      33,
      0,
      0,
      77,
      83,
      71,
      95,
      48,
      49,
      50,
      95,
      48,
      95,
      48,
      0,
      0,
      0,
      0,
      0,
      0,
      0,
      0,
      0,
      0,
      0,
      0,
      0,
      0,
      1,
      0,
      1,
      0,
      0,
      12,
      -4,
      0,
      0,
      0,
      71,
      -2,
      -14,
      5,
      -1,
      -1,
      -2,
      -15,
      65,
      -2,
      -9,
      -123,
      105,
      1,
      2,
      1,
      0,
      0,
      0,
      0,
      1,
      1,
      1,
      1,
      -2,
      -9,
      97,
      2,
      1,
      1,
      1,
      5,
      1,
      28,
      1,
      1,
      1,
      1,
      1,
      -24,
      -128,
      -127,
      -25,
      -120,
      -70,
      -27,
      -83,
      -112,
      -28,
      -67,
      -96,
      -25,
      -100,
      -97,
      -26,
      -104,
      -81,
      -25,
      -102,
      -124,
      -30,
      -128,
      -90,
      -30,
      -128,
      -90,
      13,
      10,
      -2,
      -15,
      33,
      0,
      0,
      0,
      0,
      13,
      76,
      0,
      0,
      13,
      89,
      -26,
      -106,
      -121,
      -27,
      -112,
      -119,
      -25,
      -120,
      -70,
      -25,
      -120,
      -70,
      0,
      -27,
      -123,
      -119,
      -27,
      -83,
      -112,
      -27,
      -87,
      -122,
      -27,
      -87,
      -122,
      0,
      0,
      0,
      2,
      4,
      4,
      4,
      4,
      4,
      4,
      4,
      4,
      4,
      4,
      4,
      4,
      2,
      22,
      2,
      112,
      2,
      116,
      15,
      -54,
      2,
      46,
      82,
      2,
      118,
      15,
      -24,
      2,
      114,
      23,
      9,
      2,
      2,
      120,
      76,
      74,
      40,
      2
    ]
  }
}